csview/__init__.py
csview/csview.css
csview/csview.py
csview-0.1.3.dist-info/LICENSE
csview-0.1.3.dist-info/METADATA
csview-0.1.3.dist-info/WHEEL
csview-0.1.3.dist-info/entry_points.txt
csview-0.1.3.dist-info/RECORD
