Metadata-Version: 2.3
Name: csview
Version: 0.1.3
Summary: Text-based CSV viewer for the terminal
License: MIT
Author: Danny Stewart
Author-email: danny@stewart.cc
Requires-Python: >=3.12,<4.0
Classifier: License :: OSI Approved :: MIT License
Classifier: Programming Language :: Python :: 3
Classifier: Programming Language :: Python :: 3.12
Classifier: Programming Language :: Python :: 3.13
Requires-Dist: click (>=8.1.8,<9.0.0)
Requires-Dist: matplotlib (>=3.10.1,<4.0.0)
Requires-Dist: openpyxl (>=3.1.5,<4.0.0)
Requires-Dist: pandas (>=2.2.3,<3.0.0)
Requires-Dist: polykit (>=0.8.0,<0.9.0)
Requires-Dist: rich (<=13.9.4)
Requires-Dist: seaborn (>=0.13.2,<0.14.0)
Requires-Dist: tabulate (>=0.9.0,<0.10.0)
Requires-Dist: textual (>=3.0.1,<4.0.0)
